flexible_datetime/__init__.py
flexible_datetime/flex_datetime.py
flexible_datetime/flex_time.py
flexible_datetime/flexible_datetime.py
flexible_datetime/py.typed
flexible_datetime/pydantic_arrow.py
flexible_datetime/time_utils.py
flexible_datetime-1.0.10.dist-info/METADATA
flexible_datetime-1.0.10.dist-info/WHEEL
flexible_datetime-1.0.10.dist-info/licenses/LICENSE
flexible_datetime-1.0.10.dist-info/RECORD
