Metadata-Version: 2.4
Name: flexible-datetime
Version: 1.0.10
Summary: Flexible datetime handling for Python
License-Expression: MIT
License-File: LICENSE
Classifier: License :: OSI Approved :: MIT License
Classifier: Programming Language :: Python :: 3
Classifier: Programming Language :: Python :: 3.12
Classifier: Programming Language :: Python :: 3.13
Classifier: Topic :: Software Development :: Build Tools
Classifier: Topic :: Software Development :: Libraries :: Python Modules
Requires-Python: >=3.11
Requires-Dist: arrow>=1.3.0
Requires-Dist: pydantic>=2.10.6
